{
    "version": "2.6.0",
    "description": "Restore and gather all visible windows to the primary monitor on Windows 11",
    "homepage": "https://github.com/aviscaerulea/winfocus",
    "license": "MIT",
    "architecture": {
        "64bit": {
            "url": "https://github.com/aviscaerulea/winfocus/releases/download/v2.6.0/winfocus-v2.6.0-x64.zip",
            "hash": "60fffb46b85110fd4e658e1a0bd96cf035130086249f6615c41ac12899476b1b"
        }
    },
    "bin": "winfocus.exe",
    "persist": "winfocus.toml",
    "checkver": {
        "github": "https://github.com/aviscaerulea/winfocus"
    },
    "autoupdate": {
        "architecture": {
            "64bit": {
                "url": "https://github.com/aviscaerulea/winfocus/releases/download/v$version/winfocus-v$version-x64.zip"
            }
        }
    }
}
